Workbook

Sheet games
A1: DOC_ID | B1: CENTRE | C1: STATUS | D1: PLACE_ID | E1: LOCATION | F1: DATE
A2: 00D0EPKylfi3bz0wt7ZI | B2: Game 13 foot indoor | C2: canceled | D2: ChIJNSDvlsXryRIRUXao9hwB79I | E2: 43.41258939999999&5.366617 | F2: 2023-10-16T18:30:00.000Z
A3: 00HTbiPPxn91ynn7qR1L | B3: UrbanSoccer - Porte d'Aubervilliers | C3: played | D3: ChIJ0dXjDCZs5kcRvX0EpMwxsUY | E3: 48.9074912&2.3746518 | F3: 2024-01-07T10:00:00.000Z
A4: 00KQmUOvGxj4u2l7AKnP | B4: UrbanSoccer - Lille Lezennes | C4: canceled | E4: 50.6169533&3.0995426 | F4: 2023-09-05T20:00:00.000Z
A5: 00LrLdN1UmDSaFH0PwoM | B5: We Are Sports | C5: canceled | D5: ChIJFZU5oBHC9EcRJTFrSkI1xxg | E5: 45.7113247&4.8761886 | F5: 2023-10-29T09:00:00.000Z
A6: 00NjDYA0rVMKo7x0Z4iR | B6: Footbox | C6: published | D6: ChIJY-WkusIR5kcR-tEad3UtaSQ | E6: 48.9022789&2.582647 | F6: 2024-01-07T17:00:00.000Z
A7: 00eHWDuZqESMgqL1WRhK | B7: UrbanSoccer La D√©fense | C7: draft | D7: ChIJh4rnfVhk5kcRV2Q-ZKdm8vA | E7: 48.8996456&2.2216773 | F7: 2023-12-27T17:45:00.000Z
A8: 00pEnMODhbHxhdN9bcOs | B8: Stadium Thiais | C8: played | E8: 48.7511024&2.3713455 | F8: 2023-10-31T16:30:00.000Z
A9: 00pmhG4IkKds1ZDVdsso | B9: Foot POWER 5 | C9: canceled | E9: 48.960066&2.2061913 | F9: 2024-02-06T17:00:00.000Z
A10: 00zKqorbhZeaIg0UDJDF | B10: Le 13 - Foot en salle - Marseille | C10: canceled | D10: ChIJR62kUm_ByRIRDnGQqGCeUVQ | E10: 43.33370070000001&5.370389599999999 | F10: 2024-01-23T22:15:00.000Z
A11: 01DNdi3KlujTX6skrg3g | B11: Game 13 foot indoor | C11: played | D11: ChIJNSDvlsXryRIRUXao9hwB79I | E11: 43.41258939999999&5.366617 | F11: 2024-01-23T20:30:00.000Z
A12: 01JxNMzkCrf2HKGsi0nV | B12: LE FIVE Carri√®res-sous-Poissy | C12: played | E12: 48.9468144&2.0230574 | F12: 2023-09-08T20:00:00.000Z
A13: 01QB6kfRmLf35vYRDrOE | B13: Stade de foot Pompadour | C13: published | D13: ChIJZWcRAWN15kcR0aRSqeWgmaI | E13: 48.773015&2.432866 | F13: 2024-01-06T11:00:00.000Z
A14: 01ZbJa9fM9COMXnLynCM | B14: LE FIVE Paris 18 | C14: played | D14: ChIJpVT4_n1u5kcRzji6FdTBXXo | E14: 48.8978522&2.3700234 | F14: 2024-01-10T17:30:00.000Z
A15: 01aiIXTWgJgnxa4xFnIt | B15: LE FIVE Paris 17 | C15: played | E15: 48.900032&2.3213449 | F15: 2023-09-02T15:00:00.000Z
A16: 01fMyFWQrEhSbW2upztG | B16: Stadium Thiais | C16: draft | D16: ChIJ64X9jzx05kcRsHvSfOv6UcA | E16: 48.7511024&2.3713455 | F16: 2023-12-02T16:00:00.000Z
A17: 029oObNC5LKinw1cS1l2 | B17: UrbanSoccer - Marne-La-Vall√©e | C17: draft | D17: ChIJ6bDBiosP5kcROXiloHzSdhc | E17: 48.82658600000001&2.6296937
A18: 02P4Ad46JMOKQr3nHXVI | B18: LE FIVE Montreuil | C18: published | E18: 48.8613036&2.4653095 | F18: 2024-02-27T09:00:00.000Z
A19: 02VDY3BeIYvvYul4Tl3O | B19: UrbanSoccer - Puteaux | C19: played | D19: ChIJM_sC0-Nk5kcRhL1y_EFIje8 | E19: 48.8836397&2.2312283 | F19: 2023-11-04T12:30:00.000Z
A20: 02VdYJG2vTOPskH6b3Ap | B20: LE FIVE Marville - La Courneuve | C20: published | E20: 48.9361223&2.3872592 | F20: 2023-10-03T12:00:00.000Z
A21: 02WXbhGT2w7FtZZbdOEJ | B21: UrbanSoccer - Puteaux | C21: canceled | E21: 48.8836397&2.2312283 | F21: 2023-09-22T18:00:00.000Z
A22: 02h87XMAB9N8Lny6HT0I | B22: UrbanSoccer - Puteaux | C22: canceled | D22: ChIJM_sC0-Nk5kcRhL1y_EFIje8 | E22: 48.8836397&2.2312283 | F22: 2023-10-20T17:15:00.000Z
A23: 02lQ08jQ1qczkosCpNjh | B23: UrbanSoccer - Porte d'Aubervilliers | C23: played | E23: 48.9074912&2.3746518 | F23: 2023-09-10T15:30:00.000Z
A24: 02oe8khjbfJUb1QNXSTN | B24: UrbanSoccer Orsay | C24: canceled | D24: ChIJpZIJg7J45kcRrKWKhtbfnEQ | E24: 48.70829&2.17794 | F24: 2023-12-16T10:00:00.000Z
A25: 02u5zUYR9AcOED2YnEYT | B25: Cr√©teil Pompadour | C25: published | D25: ChIJX79lm6d05kcRdvnIvrrCKDc | E25: 48.771485&2.4353447 | F25: 2024-01-21T12:00:00.000Z
A26: 03Alcz66wSkAUuELRV7P | B26: STADE PIERRE BOURDAN | C26: played | D26: ChIJlzXk7HLr9EcR8P0J9oTn_Pk | E26: 45.79243109999999&4.840371699999999 | F26: 2023-10-01T08:00:00.000Z
A27: 03DtLtqnJ2ZNo2pk6TTK | B27: UrbanSoccer La D√©fense | C27: played | D27: ChIJh4rnfVhk5kcRV2Q-ZKdm8vA | E27: 48.8996456&2.2216773 | F27: 2023-11-19T18:00:00.000Z
A28: 03QkqZQKOCy1BQmtdDwH | B28: Stadium Thiais | C28: played | E28: 48.7511024&2.3713455 | F28: 2023-09-05T17:30:00.000Z
A29: 03RR9bdwDPRyQ33rcYFw | B29: UrbanSoccer - Quai d'Ivry | C29: played | D29: ChIJfXxYJ0xy5kcRw9xTkF6-FZQ | E29: 48.8199815&2.3936307 | F29: 2023-11-19T19:15:00.000Z
A30: 03U0BusYBA2ehxFNqCat | B30: LE FIVE Cr√©teil | C30: published | E30: 48.7643086&2.4706522 | F30: 2024-03-04T16:00:00.000Z
A31: 040MLBU2bXcWnGINBKVl | B31: LE FIVE Marville - La Courneuve | C31: canceled | D31: ChIJ2dHdMZxr5kcR0aKYHYsp0pY | E31: 48.9364404&2.3869147 | F31: 2023-11-09T17:30:00.000Z
A32: 04L33X6SUHv6nWtJ0mku | B32: Le 13 - Foot en salle - Marseille | C32: canceled | D32: ChIJR62kUm_ByRIRDnGQqGCeUVQ | E32: 43.33370070000001&5.370389599999999 | F32: 2023-11-21T19:00:00.000Z
A33: 04PEEV3iRE8sTvk6gCts | B33: Stadium Thiais | C33: published | E33: 48.7511024&2.3713455 | F33: 2023-09-04T17:00:00.000Z
A34: 04gJdGYyVUukYA8MRdXI | B34: Stadium Thiais | C34: played | D34: ChIJ64X9jzx05kcRsHvSfOv6UcA | E34: 48.7511024&2.3713455 | F34: 2024-01-24T18:00:00.000Z
A35: 050PGY1dw4L8S9C2Ao3l | B35: Abd Drive | C35: played | D35: ChIJCVBWxGht5kcRclC3u2EvPKs | E35: 48.86598919999999&2.4308229 | F35: 2023-10-07T07:00:00.000Z
A36: 05HbahbEePLpDe7VbADa | B36: Top Ten | C36: published | E36: 48.8729106&2.6840919 | F36: 2023-10-13T10:00:00.000Z
A37: 05JgYAaYkVgfSGckt9yo | B37: UrbanSoccer - Puteaux | C37: draft | E37: 48.8836397&2.2312283
A38: 05QHO5TE7IcXtfooRPjI | B38: Top Ten | C38: published | D38: ChIJfXprBx4b5kcRmhe-5pLZUek | E38: 48.8729106&2.6840919 | F38: 2023-10-16T16:30:00.000Z
A39: 05RXibHd2A01CjfuXl6P | B39: Stade Makowski | C39: played | D39: ChIJvShnxJpt5kcRwdqlaq1s3E0 | E39: 48.9090365&2.436058 | F39: 2023-10-08T08:00:00.000Z
A40: 05jTyZfZ3VcOTC3urnmw | B40: LE FIVE Bezons | C40: played | D40: ChIJ71Mv0Wpk5kcRg-H9x7L-dXo | E40: 48.9190419&2.2117725 | F40: 2023-10-30T18:30:00.000Z
A41: 05oao71c7MCFtLT4l9P1 | B41: Rue du Mus√©e | C41: canceled | D41: ChIJ4ypzX6B15kcRFesay1dBJco | E41: 48.71676&2.39852 | F41: 2023-10-08T08:30:00.000Z
A42: 05yYJ2TXkJ5M4o4SUfQ2 | B42: LE FIVE Sarcelles | C42: played | D42: ChIJ6_q3Fxhq5kcRCpoEwnoXX1Q | E42: 48.99782219999999&2.3902225 | F42: 2023-12-22T18:50:00.000Z
A43: 06CUvCTVWzJtwBolKi2B | B43: LE FIVE OL | C43: canceled | D43: ChIJmz3whejH9EcR3j9ApNRukKE | E43: 45.7673403&4.9802325 | F43: 2024-01-13T18:00:00.000Z
A44: 06VBLceiG3aLk7yGnq2Q | B44: UrbanSoccer Guyancourt | C44: canceled | D44: ChIJmdX-2c-A5kcRj1wtOS8rZmo | E44: 48.7722091&2.0600292 | F44: 2023-10-06T19:00:00.000Z
A45: 06Vy02xSUHJsLo5oZzbE | B45: Hoops Factory Paris-Villette | C45: canceled | E45: 48.9046968&2.3794611 | F45: 2023-09-12T19:00:00.000Z
A46: 06j5ggzW2o0k6axRgYqf | B46: FOOT IN FIVE | C46: played | D46: ChIJoUR0syFp5kcRUlStnwluaYY | E46: 48.9552257&2.3328346 | F46: 2023-09-30T16:30:00.000Z
A47: 06jD0cNAokujpj9OYRI1 | B47: Stade de la Tour aux Parachutes | C47: published | E47: 48.8175176&2.3643354 | F47: 2023-09-22T13:45:00.000Z
A48: 06uQUlGXUNx9wLpUoznL | B48: UrbanSoccer La D√©fense | C48: played | D48: ChIJh4rnfVhk5kcRV2Q-ZKdm8vA | E48: 48.8996456&2.2216773 | F48: 2023-10-27T20:30:00.000Z
A49: 078bCl8X8gFBRzpy1jMI | B49: Le Luth | C49: played | E49: 48.93177&2.28867 | F49: 2023-11-01T11:00:00.000Z
A50: 07F7y8GPwNcd9aNfWB9G | B50: Stade √âlisabeth | C50: played | D50: ChIJkXj9tq5x5kcROlxynHzTh9o | E50: 48.8207737&2.3270972 | F50: 2023-10-11T17:00:00.000Z
A51: 07Gv22yXgYBEqVP3Hae7 | B51: UrbanSoccer La D√©fense | C51: draft | D51: ChIJh4rnfVhk5kcRV2Q-ZKdm8vA | E51: 48.8996456&2.2216773 | F51: 2024-01-09T20:30:00.000Z
A52: 07ORwHTlpDKFlJIsUABZ | B52: UrbanSoccer - Quai d'Ivry | C52: played | E52: 48.8199815&2.3936307 | F52: 2023-09-03T07:45:00.000Z
A53: 07PvO56tcxnggo5xPD0L | B53: Stade des Bords de Marne | C53: canceled | E53: 48.8531646&2.5526833 | F53: 2023-09-16T08:00:00.000Z
A54: 07VyfoMF7XtkWowkAALi | B54: UrbanSoccer - Puteaux | C54: draft | D54: ChIJM_sC0-Nk5kcRhL1y_EFIje8 | E54: 48.8836397&2.2312283
A55: 07sUBrsZRrovz9s0a2mW | B55: Play Soccer | C55: played | D55: ChIJQ-UxZn-5rhIRKWoQydM5T9s | E55: 43.5512023&1.4098927 | F55: 2023-10-12T17:00:00.000Z
A56: 07ujWLXNPoWrq99V4jK1 | B56: Sport dans la Ville Rh√¥ne-Alpes | C56: played | D56: ChIJoUEDcmvr9EcRILCz6hDCQ2o | E56: 45.7811703&4.8081568 | F56: 2023-12-13T18:00:00.000Z
A57: 082Rin4WjlxjSMq4LLDi | B57: Evolution Football | C57: played | D57: ChIJX0YulIi8yRIRnGh62u3UXTQ | E57: 43.2836074&5.52356 | F57: 2024-01-03T18:30:00.000Z
A58: 08AZ42bXpaZ2UEocVXAF | B58: Centre Sportif Lionel Terray | C58: played | D58: ChIJo7Jtup935kcRUd9lcEtEKzc | E58: 48.7349914&2.287439 | F58: 2023-12-10T08:30:00.000Z
A59: 08CBL8DJkFNfb3Wzpnco | B59: UrbanSoccer Guyancourt | C59: played | D59: ChIJmdX-2c-A5kcRj1wtOS8rZmo | E59: 48.7722091&2.0600292 | F59: 2023-09-27T16:00:00.000Z
A60: 08EBQbUJcjASvcwf4DaP | B60: Stadium Thiais | C60: canceled | D60: ChIJ64X9jzx05kcRsHvSfOv6UcA | E60: 48.7511024&2.3713455 | F60: 2023-11-09T18:00:00.000Z
A61: 08ebIyNCTqfRhl4EJh5Z | B61: LE FIVE Bezons | C61: played | D61: ChIJ71Mv0Wpk5kcRg-H9x7L-dXo | E61: 48.9190419&2.2117725 | F61: 2023-10-21T15:00:00.000Z
A62: 08lSyKsyT3Uo3cPyt7Bm | B62: LE FIVE Paris 18 | C62: published | D62: ChIJpVT4_n1u5kcRzji6FdTBXXo | E62: 48.8978522&2.3700234 | F62: 2023-12-18T21:00:00.000Z
A63: 09ALDJSxcbHbF4k5EW4K | B63: LE FIVE Montreuil | C63: published | E63: 48.8613036&2.4653095 | F63: 2024-02-23T16:30:00.000Z
A64: 09V0R71ORsL8qPofpz2m | B64: LE FIVE Montreuil | C64: published | E64: 48.8613036&2.4653095 | F64: 2024-01-20T15:00:00.000Z
A65: 09ZQftZMXs2H61xYNYX4 | B65: Foot-Max Argenteuil | C65: published | D65: ChIJi9oIzaRm5kcRJYcK7QsdRMU | E65: 48.9501632&2.2093946 | F65: 2023-11-10T20:00:00.000Z
A66: 09buiinuJzAiNugUEFfk | B66: Stadium Thiais | C66: played | D66: ChIJ64X9jzx05kcRsHvSfOv6UcA | E66: 48.7511024&2.3713455 | F66: 2023-10-29T15:00:00.000Z
A67: 09z2TWhR8MwcrFFNCzkq | B67: Parc Interd√©partemental des Sports du Tremblay | C67: published | D67: ChIJBVkfrQ4N5kcRGi-XnNQN_yo | E67: 48.8281085&2.491365
A68: 09znPFTdPKiYDRfZQlbZ | B68: Ball In d'Or Dreux | C68: published | D68: ChIJgRwhLzZV4UcRZ1kZ41ivPqU | E68: 48.7468231&1.3611978 | F68: 2023-12-29T18:00:00.000Z
A69: 0AFD2rDgs6RoMIGGOU4g | B69: LE FIVE Paris 18 | C69: played | D69: ChIJpVT4_n1u5kcRzji6FdTBXXo | E69: 48.8978522&2.3700234 | F69: 2024-01-06T20:30:00.000Z
A70: 0AM5VepkV74f16Jh9ZCy | B70: LE FIVE Paris 13 | C70: canceled | E70: 48.8181615&2.3658793 | F70: 2023-09-10T12:00:00.000Z
A71: 0ANs9z7tdkUoHd6RoFVc | B71: Foot POWER 5 | C71: canceled | D71: ChIJuTCIFshm5kcRBtEQJ76dAzc | E71: 48.960066&2.2061913 | F71: 2023-12-09T22:30:00.000Z
A72: 0AQ3iN0JOz5fy9FTYvhr | B72: UrbanSoccer - Quai d'Ivry | C72: played | D72: ChIJfXxYJ0xy5kcRw9xTkF6-FZQ | E72: 48.8199815&2.3936307 | F72: 2023-09-25T17:00:00.000Z
A73: 0AlfRmgBwrrU56BV7Z04 | B73: UrbanSoccer - Puteaux | C73: played | D73: ChIJM_sC0-Nk5kcRhL1y_EFIje8 | E73: 48.8836397&2.2312283 | F73: 2023-11-08T21:00:00.000Z
A74: 0AnhF8k3fC8lgOxonR9g | B74: LE FIVE Paris 18 | C74: canceled | D74: ChIJpVT4_n1u5kcRzji6FdTBXXo | E74: 48.8978522&2.3700234 | F74: 2023-12-09T12:15:00.000Z
A75: 0B2hLkdnbdZy3U35zWKo | B75: Stade Pierre Letessier | C75: published | D75: ChIJmcO_CLgS5kcR_tYXn2vhXNs | E75: 48.8750074&2.4964236 | F75: 2023-12-31T09:45:00.000Z
A76: 0B8TCWpjV8qGHnCbPERr | B76: UrbanSoccer La D√©fense | C76: played | D76: ChIJh4rnfVhk5kcRV2Q-ZKdm8vA | E76: 48.8996456&2.2216773 | F76: 2023-11-01T17:45:00.000Z
A77: 0BKavgzC7CFMj4wPjjoU | B77: Top Ten | C77: played | D77: ChIJfXprBx4b5kcRmhe-5pLZUek | E77: 48.8729106&2.6840919 | F77: 2023-10-09T15:00:00.000Z
A78: 0CAvOPZHnr0dtiKnLt2R | B78: Parc Interd√©partemental des Sports du Tremblay | C78: canceled | D78: ChIJBVkfrQ4N5kcRGi-XnNQN_yo | E78: 48.8281085&2.491365 | F78: 2023-11-18T15:30:00.000Z
A79: 0CB33Z4jnM9nlDp0oAoI | B79: Stade Parfait Lebourg | C79: canceled | D79: ChIJXdP-tHUK5kcRzMpBMEOwKU8 | E79: 48.69499829999999&2.5092223 | F79: 2023-10-25T18:15:00.000Z
A80: 0CZJzbvNMjahumY1U3ad | B80: Evolution Football | C80: played | D80: ChIJX0YulIi8yRIRnGh62u3UXTQ | E80: 43.2836074&5.52356 | F80: 2023-09-26T17:30:00.000Z
A81: 0Ck89PvAmzjG3zjKv9if | B81: Play Soccer | C81: played | D81: ChIJQ-UxZn-5rhIRKWoQydM5T9s | E81: 43.5512023&1.4098927 | F81: 2023-10-29T17:30:00.000Z
A82: 0CkRc7K52hLJVC2s3yes | B82: √âlite 5 Soccer | C82: canceled | D82: ChIJ5-jfdlZk5kcRYIaELgvikaM | E82: 48.9009153&2.2297275 | F82: 2023-11-09T17:30:00.000Z
... A86: 0DPA0V2ieui5DQmmiAc1 | B86: UrbanSoccer La D√©fense | C86: canceled | D86: ChIJh4rnfVhk5kcRV2Q-ZKdm8vA | E86: 48.8996456&2.2216773 | F86: 2023-10-25T18:00:00.000Z
A87: 0DVIDjAMEj7HRqp1kzJx | B87: Stade de foot Pompadour | C87: canceled | E87: 48.773015&2.432866 | F87: 2023-09-03T11:00:00.000Z
A88: 0Dd3wQ6mBU19TluHUJqw | B88: UrbanSoccer La D√©fense | C88: played | D88: ChIJh4rnfVhk5kcRV2Q-ZKdm8vA | E88: 48.8996456&2.2216773 | F88: 2023-12-23T15:00:00.000Z
A89: 0Dj26hTcMpWTICuX4lFU | B89: Monclub Futbol | C89: played | D89: ChIJGbxxaamUyRIRgGvhHnhJStA | E89: 43.4299152&5.4001974 | F89: 2023-12-21T18:00:00.000Z
A90: 0DpKJB4RF2d3yhhUD8xe | B90: Foot POWER 5 | C90: played | E90: 48.960066&2.2061913 | F90: 2023-09-16T10:00:00.000Z
A91: 0DpWUgoEAzVtekPGJ80g | B91: UrbanSoccer La D√©fense | C91: canceled | D91: ChIJh4rnfVhk5kcRV2Q-ZKdm8vA | E91: 48.8996456&2.2216773 | F91: 2024-01-03T11:00:00.000Z
A92: 0DxCXTr0GkqdLCFL9q9s | B92: UrbanSoccer - Lille Lezennes | C92: played | D92: ChIJR3ro5nTWwkcRfM_S3Be9HjI | E92: 50.6169533&3.0995426 | F92: 2023-12-30T18:00:00.000Z
A93: 0EUq7aKrcxHGNaE5biJZ | B93: Evolution Football | C93: played | D93: ChIJX0YulIi8yRIRnGh62u3UXTQ | E93: 43.2836074&5.52356 | F93: 2023-12-11T20:30:00.000Z
A94: 0EZIYlUXVUXB6Y8YjO3y | B94: Monclub Futbol | C94: played | D94: ChIJGbxxaamUyRIRgGvhHnhJStA | E94: 43.4299152&5.4001974 | F94: 2023-10-25T19:00:00.000Z
A95: 0EbyFa7uBdJSGNiWMMI1 | B95: UrbanSoccer - Quai d'Ivry | C95: canceled | D95: ChIJfXxYJ0xy5kcRw9xTkF6-FZQ | E95: 48.8199815&2.3936307 | F95: 2023-10-08T13:30:00.000Z
A96: 0EhRNUdGVNoS4vmHR3Hr | B96: Play Soccer | C96: played | D96: ChIJQ-UxZn-5rhIRKWoQydM5T9s | E96: 43.5512023&1.4098927 | F96: 2023-10-24T18:00:00.000Z
A97: 0EnNBiXbFPUU3Cn0Y6B2 | B97: Play Soccer | C97: played | E97: 43.5512023&1.4098927 | F97: 2023-09-07T16:30:00.000Z
A98: 0ErIw8YEoWQsGTsDyEey | B98: UrbanSoccer - Puteaux | C98: played | D98: ChIJM_sC0-Nk5kcRhL1y_EFIje8 | E98: 48.8836397&2.2312283 | F98: 2023-09-28T10:00:00.000Z
A99: 0Ev4SGuNkbAInRIHyALh | B99: Top Ten | C99: published | E99: 48.8729106&2.6840919 | F99: 2023-11-16T22:00:00.000Z
A100: 0EwKRW03i3sJdiIqh9HN | B100: UrbanSoccer - Marne-La-Vall√©e | C100: canceled | D100: ChIJ6bDBiosP5kcROXiloHzSdhc | E100: 48.82658600000001&2.6296937 | F100: 2023-10-01T07:00:00.000Z
A101: 0F1hINcAPYLyA0Ti76Dw | B101: Stadium Thiais | C101: published | E101: 48.7511024&2.3713455 | F101: 2023-11-03T16:30:00.000Z
A102: 0F2QttKLhc0PImskn1dF | B102: Stade Fr√®res Nouali. | C102: published | D102: ChIJBx8zKDXzeA0RX_Z8eLNf2Yg | E102: 34.8504865&-1.7316045 | F102: 2023-11-29T16:00:00.000Z
A103: 0FJTEyKf3TUKuKhs3M4h | B103: Footsal | C103: played | D103: ChIJa7HS298pw0cRMoVDj0XqVdI | E103: 50.6397895&3.1251337 | F103: 2024-01-11T19:00:00.000Z
...

Sheet Sheet1
A1: DOC_ID | B1: CENTRE | C1: STATUS | D1: PLACE_ID | E1: LOCATION | F1: DATE
A2: 00D0EPKylfi3bz0wt7ZI | B2: Game 13 foot indoor | C2: canceled | D2: ChIJNSDvlsXryRIRUXao9hwB79I | E2: 43.41258939999999&5.366617 | F2: 2023-10-16T18:30:00.000Z
A3: 00HTbiPPxn91ynn7qR1L | B3: UrbanSoccer - Porte d'Aubervilliers | C3: played | D3: ChIJ0dXjDCZs5kcRvX0EpMwxsUY | E3: 48.9074912&2.3746518 | F3: 2024-01-07T10:00:00.000Z
A4: 00LrLdN1UmDSaFH0PwoM | B4: We Are Sports | C4: canceled | D4: ChIJFZU5oBHC9EcRJTFrSkI1xxg | E4: 45.7113247&4.8761886 | F4: 2023-10-29T09:00:00.000Z
A5: 00NjDYA0rVMKo7x0Z4iR | B5: Footbox | C5: published | D5: ChIJY-WkusIR5kcR-tEad3UtaSQ | E5: 48.9022789&2.582647 | F5: 2024-01-07T17:00:00.000Z
A6: 00zKqorbhZeaIg0UDJDF | B6: Le 13 - Foot en salle - Marseille | C6: canceled | D6: ChIJR62kUm_ByRIRDnGQqGCeUVQ | E6: 43.33370070000001&5.370389599999999 | F6: 2024-01-23T22:15:00.000Z
A7: 01DNdi3KlujTX6skrg3g | B7: Game 13 foot indoor | C7: played | D7: ChIJNSDvlsXryRIRUXao9hwB79I | E7: 43.41258939999999&5.366617 | F7: 2024-01-23T20:30:00.000Z
A8: 01QB6kfRmLf35vYRDrOE | B8: Stade de foot Pompadour | C8: published | D8: ChIJZWcRAWN15kcR0aRSqeWgmaI | E8: 48.773015&2.432866 | F8: 2024-01-06T11:00:00.000Z
A9: 01ZbJa9fM9COMXnLynCM | B9: LE FIVE Paris 18 | C9: played | D9: ChIJpVT4_n1u5kcRzji6FdTBXXo | E9: 48.8978522&2.3700234 | F9: 2024-01-10T17:30:00.000Z
A10: 02VDY3BeIYvvYul4Tl3O | B10: UrbanSoccer - Puteaux | C10: played | D10: ChIJM_sC0-Nk5kcRhL1y_EFIje8 | E10: 48.8836397&2.2312283 | F10: 2023-11-04T12:30:00.000Z
A11: 02h87XMAB9N8Lny6HT0I | B11: UrbanSoccer - Puteaux | C11: canceled | D11: ChIJM_sC0-Nk5kcRhL1y_EFIje8 | E11: 48.8836397&2.2312283 | F11: 2023-10-20T17:15:00.000Z
A12: 02oe8khjbfJUb1QNXSTN | B12: UrbanSoccer Orsay | C12: canceled | D12: ChIJpZIJg7J45kcRrKWKhtbfnEQ | E12: 48.70829&2.17794 | F12: 2023-12-16T10:00:00.000Z
... A40: 09buiinuJzAiNugUEFfk | B40: Stadium Thiais | C40: played | D40: ChIJ64X9jzx05kcRsHvSfOv6UcA | E40: 48.7511024&2.3713455 | F40: 2023-10-29T15:00:00.000Z
A41: 09z2TWhR8MwcrFFNCzkq | B41: Parc Interd√©partemental des Sports du Tremblay | C41: published | D41: ChIJBVkfrQ4N5kcRGi-XnNQN_yo | E41: 48.8281085&2.491365
A42: 09znPFTdPKiYDRfZQlbZ | B42: Ball In d'Or Dreux | C42: published | D42: ChIJgRwhLzZV4UcRZ1kZ41ivPqU | E42: 48.7468231&1.3611978 | F42: 2023-12-29T18:00:00.000Z
A43: 0AFD2rDgs6RoMIGGOU4g | B43: LE FIVE Paris 18 | C43: played | D43: ChIJpVT4_n1u5kcRzji6FdTBXXo | E43: 48.8978522&2.3700234 | F43: 2024-01-06T20:30:00.000Z
A44: 0ANs9z7tdkUoHd6RoFVc | B44: Foot POWER 5 | C44: canceled | D44: ChIJuTCIFshm5kcRBtEQJ76dAzc | E44: 48.960066&2.2061913 | F44: 2023-12-09T22:30:00.000Z
A45: 0AQ3iN0JOz5fy9FTYvhr | B45: UrbanSoccer - Quai d'Ivry | C45: played | D45: ChIJfXxYJ0xy5kcRw9xTkF6-FZQ | E45: 48.8199815&2.3936307 | F45: 2023-09-25T17:00:00.000Z
A46: 0AlfRmgBwrrU56BV7Z04 | B46: UrbanSoccer - Puteaux | C46: played | D46: ChIJM_sC0-Nk5kcRhL1y_EFIje8 | E46: 48.8836397&2.2312283 | F46: 2023-11-08T21:00:00.000Z
A47: 0AnhF8k3fC8lgOxonR9g | B47: LE FIVE Paris 18 | C47: canceled | D47: ChIJpVT4_n1u5kcRzji6FdTBXXo | E47: 48.8978522&2.3700234 | F47: 2023-12-09T12:15:00.000Z
A48: 0B2hLkdnbdZy3U35zWKo | B48: Stade Pierre Letessier | C48: published | D48: ChIJmcO_CLgS5kcR_tYXn2vhXNs | E48: 48.8750074&2.4964236 | F48: 2023-12-31T09:45:00.000Z
A49: 0B8TCWpjV8qGHnCbPERr | B49: UrbanSoccer La D√©fense | C49: played | D49: ChIJh4rnfVhk5kcRV2Q-ZKdm8vA | E49: 48.8996456&2.2216773 | F49: 2023-11-01T17:45:00.000Z
A50: 0BKavgzC7CFMj4wPjjoU | B50: Top Ten | C50: played | D50: ChIJfXprBx4b5kcRmhe-5pLZUek | E50: 48.8729106&2.6840919 | F50: 2023-10-09T15:00:00.000Z
A51: 0CAvOPZHnr0dtiKnLt2R | B51: Parc Interd√©partemental des Sports du Tremblay | C51: canceled | D51: ChIJBVkfrQ4N5kcRGi-XnNQN_yo | E51: 48.8281085&2.491365 | F51: 2023-11-18T15:30:00.000Z
A52: 0CB33Z4jnM9nlDp0oAoI | B52: Stade Parfait Lebourg | C52: canceled | D52: ChIJXdP-tHUK5kcRzMpBMEOwKU8 | E52: 48.69499829999999&2.5092223 | F52: 2023-10-25T18:15:00.000Z
A53: 0CZJzbvNMjahumY1U3ad | B53: Evolution Football | C53: played | D53: ChIJX0YulIi8yRIRnGh62u3UXTQ | E53: 43.2836074&5.52356 | F53: 2023-09-26T17:30:00.000Z
... A123: 0SWOAQcuTuZgvPrU7i0Q | B123: Terre 2 Foot | C123: published | D123: ChIJK9S0wlOj4EcRx17lcyjFr0c | E123: 49.9048022&1.1127586 | F123: 2023-12-02T19:00:00.000Z
A124: 0SWhr7lMTMnqXi6X6hHq | B124: LE FIVE Paris 18 | C124: published | D124: ChIJpVT4_n1u5kcRzji6FdTBXXo | E124: 48.8978522&2.3700234
A125: 0SdIsxxRS9znubcVvlJi | B125: Play Soccer | C125: canceled | D125: ChIJQ-UxZn-5rhIRKWoQydM5T9s | E125: 43.5512023&1.4098927 | F125: 2024-01-09T16:30:00.000Z
A126: 0SmuLKeW8AcB6YbWCJyt | B126: UrbanSoccer La D√©fense | C126: canceled | D126: ChIJh4rnfVhk5kcRV2Q-ZKdm8vA | E126: 48.8996456&2.2216773 | F126: 2023-11-20T19:15:00.000Z
A127: 0SzI6KX7dqouPz656z0V | B127: LE FIVE Paris 18 | C127: canceled | D127: ChIJpVT4_n1u5kcRzji6FdTBXXo | E127: 48.8978522&2.3700234 | F127: 2023-11-26T19:00:00.000Z
A128: 0T2kdAuJo018LI3ai2s6 | B128: UrbanSoccer - Toulouse Montaudran | C128: canceled | D128: ChIJl772e0u8rhIR2foRX4Xa2CI | E128: 43.574642&1.4801835 | F128: 2023-11-13T21:00:00.000Z
A129: 0T93uMSer5Ein2jelq8r | B129: Urban Football Meudon | C129: canceled | D129: ChIJFeLBC2N75kcRyM1mlEZ3HjM | E129: 48.7983594&2.2102561 | F129: 2023-11-22T19:30:00.000Z
A130: 0TDWkUqLZxfzL5x2V2aS | B130: UrbanSoccer - Quai d'Ivry | C130: played | D130: ChIJfXxYJ0xy5kcRw9xTkF6-FZQ | E130: 48.8199815&2.3936307 | F130: 2023-11-08T16:15:00.000Z
A131: 0TENzMGiBauBulW0Hk9O | B131: Stadium Thiais | C131: canceled | D131: ChIJ64X9jzx05kcRsHvSfOv6UcA | E131: 48.7511024&2.3713455 | F131: 2023-09-23T10:30:00.000Z
A132: 0TLf0NvUvOfnqV34xMY1 | B132: UrbanSoccer - Puteaux | C132: canceled | D132: ChIJM_sC0-Nk5kcRhL1y_EFIje8 | E132: 48.8836397&2.2312283 | F132: 2024-01-15T18:30:00.000Z
A133: 0TOwJ8wVrwGLOP7j8VI2 | B133: LE FIVE Montreuil | C133: played | D133: ChIJJdTQjr0T5kcRZmGxtIJVy44 | E133: 48.8607303&2.4650432 | F133: 2024-01-18T21:00:00.000Z
A134: 0TjsldOGOcpoZcnpIVOZ | B134: Top Ten | C134: canceled | D134: ChIJfXprBx4b5kcRmhe-5pLZUek | E134: 48.8729106&2.6840919 | F134: 2023-12-22T18:00:00.000Z
A135: 0Tt2LUD4ZEHSZ6eiq4MZ | B135: LE FIVE Paris 13 | C135: played | D135: ChIJ_bOSChhz5kcRZMTeq_6Gdzg | E135: 48.8181615&2.3658793 | F135: 2023-11-15T17:00:00.000Z
A136: 0UAf4LmDrxu0dLtYA2BG | B136: LE FIVE Paris 13 | C136: published | D136: ChIJ_bOSChhz5kcRZMTeq_6Gdzg | E136: 48.8181615&2.3658793 | F136: 2023-12-04T19:00:00.000Z
... A203: 0l62QAKgLdtRKpZTAzQh | B203: Play Soccer | C203: played | D203: ChIJQ-UxZn-5rhIRKWoQydM5T9s | E203: 43.5512023&1.4098927 | F203: 2024-01-23T18:30:00.000Z
A204: 0llbUAIYpjh0Z9l2t4RQ | B204: F5 Foot Five | C204: published | D204: ChIJjUbM5G7A9EcRW3mlkrhyXxY | E204: 45.7857911&4.905926399999999
A205: 0lr3fV6M3qsbSoj36w4B | B205: UrbanSoccer La D√©fense | C205: played | D205: ChIJh4rnfVhk5kcRV2Q-ZKdm8vA | E205: 48.8996456&2.2216773 | F205: 2024-01-14T14:15:00.000Z
A206: 0mQyff4VB1q5eW4APeRv | B206: UrbanSoccer - Asni√®res | C206: played | D206: ChIJi5LkLT9v5kcRSlhScqEFNWs | E206: 48.92192379999999&2.3068311 | F206: 2023-11-20T18:00:00.000Z
A207: 0mWWwKdXKzIHM6zR9cP8 | B207: LE FIVE Bobigny | C207: canceled | D207: ChIJV8UONORs5kcRXxR5Qd7x130 | E207: 48.901553&2.4313304 | F207: 2023-12-31T12:00:00.000Z
A208: 0mrlVIGdtcsUvyVRj6pO | B208: Cit√© des Sports | C208: canceled | D208: ChIJ70UPf6R75kcRGb3NAV9k7Ww | E208: 48.8247744&2.2650728 | F208: 2024-01-24T11:15:00.000Z
A209: 0nAc8prEOqKioygJKjJC | B209: LE FIVE Paris 17 | C209: canceled | D209: ChIJ7eI8sFNv5kcR5xy52Wc57NU | E209: 48.900032&2.3213449 | F209: 2023-12-14T19:00:00.000Z
A210: 0nMdBz33aRjL53nhcrE6 | B210: UrbanSoccer - Lille Lezennes | C210: published | D210: ChIJR3ro5nTWwkcRfM_S3Be9HjI | E210: 50.6169533&3.0995426
A211: 0nRDZSZ3giW2QuBjT8VD | B211: Stade Olympique Yves du Manoir | C211: published | D211: ChIJYeUIntpl5kcRZsN35flVVAY | E211: 48.9292771&2.2477717 | F211: 2023-11-05T08:30:00.000Z
A212: 0ntf5R1tiGdC0D30Ewl6 | B212: Monclub Futbol | C212: hidden | D212: ChIJGbxxaamUyRIRgGvhHnhJStA | E212: 43.4299152&5.4001974 | F212: 2023-10-11T17:00:00.000Z
A213: 0o7jVdUkMNEiHZCvjKeH | B213: Parc Sainte Barbe | C213: published | D213: ChIJtw301r5w5kcRvRjidiuAyaw | E213: 48.7922897&2.2913469 | F213: 2023-12-31T23:00:00.000Z
A214: 0oD3FezeDBKR0VbhcWeJ | B214: FIVE ARENA MEAUX | C214: published | D214: ChIJ02bKSuih6EcRb796CXVbkVs | E214: 48.9539465&2.9154573 | F214: 2023-10-08T17:00:00.000Z
A215: 0oYAuE4gN9pH57GmfcyG | B215: UrbanSoccer La D√©fense | C215: played | D215: ChIJh4rnfVhk5kcRV2Q-ZKdm8vA | E215: 48.8996456&2.2216773 | F215: 2024-01-09T20:30:00.000Z
A216: 0pJSIhGKktcOCn7SdTTs | B216: LE FIVE Paris 18 | C216: played | D216: ChIJpVT4_n1u5kcRzji6FdTBXXo | E216: 48.8978522&2.3700234 | F216: 2023-12-16T10:30:00.000Z
A217: 0pdvv6BCQnnUtDc350Da | B217: Futsal | C217: played | D217: ChIJW2Aqm4nXwkcRlCVWc3BBA7g | E217: 50.6160524&3.100639 | F217: 2023-12-01T18:00:00.000Z
A218: 0q3rVJCJ3MYv58WV4hD9 | B218: Massilia FIVE | C218: canceled | D218: ChIJxZ6UmMW-yRIR7ot5DChYj4w | E218: 43.28920790000001&5.4503802 | F218: 2023-11-26T15:00:00.000Z
A219: 0qLn9KRZJCLZZRWNgdDU | B219: Stadium Thiais | C219: published | D219: ChIJ64X9jzx05kcRsHvSfOv6UcA | E219: 48.7511024&2.3713455 | F219: 2024-01-16T19:30:00.000Z
A220: 0qUQFn1MUlzrNjDRX7jo | B220: UrbanSoccer - Porte d'Aubervilliers | C220: canceled | D220: ChIJ0dXjDCZs5kcRvX0EpMwxsUY | E220: 48.9074912&2.3746518 | F220: 2023-11-02T18:15:00.000Z
A221: 0qrXW0uBMoorKH7KQGI3 | B221: Stadium Thiais | C221: canceled | D221: ChIJ64X9jzx05kcRsHvSfOv6UcA | E221: 48.7511024&2.3713455 | F221: 2023-10-19T17:00:00.000Z
A222: 0qtE5xORcLbzcVEXk12S | B222: Stade de la Tour aux Parachutes | C222: played | D222: ChIJbwsrhCpy5kcRca22Pnhr8MU | E222: 48.8175176&2.3643354 | F222: 2023-11-10T10:50:00.000Z
... A254: 0vz3MyPW3eXC8J4SmYgi | B254: UrbanSoccer - Porte d'Aubervilliers | C254: played | D254: ChIJ0dXjDCZs5kcRvX0EpMwxsUY | E254: 48.9074912&2.3746518 | F254: 2023-09-28T17:00:00.000Z
A255: 0wFazTp000CIhFCoInAp | B255: LE FIVE Paris 13 | C255: published | D255: ChIJ_bOSChhz5kcRZMTeq_6Gdzg | E255: 48.8181615&2.3658793
A256: 0wHOLps4B2hRup6jD55O | B256: F5 Foot Five | C256: canceled | D256: ChIJjUbM5G7A9EcRW3mlkrhyXxY | E256: 45.7857911&4.905926399999999 | F256: 2023-09-24T15:30:00.000Z
A257: 0wkOCf6iYWuLvXhYzj4v | B257: Parc Sainte Barbe | C257: played | D257: ChIJtw301r5w5kcRvRjidiuAyaw | E257: 48.7922897&2.2913469 | F257: 2023-12-26T11:50:00.000Z
A258: 0x0t7tF60wYa23K7BO54 | B258: LE FIVE Villette | C258: canceled | D258: ChIJTUFnQjps5kcR0pHITLTw1PI | E258: 48.9070122&2.3861459 | F258: 2023-12-31T17:00:00.000Z
A259: 0x2wkzVwpuETkujD8OEi | B259: Play Soccer | C259: canceled | D259: ChIJQ-UxZn-5rhIRKWoQydM5T9s | E259: 43.5512023&1.4098927 | F259: 2023-12-04T17:30:00.000Z
A260: 0xR5hUAIocqUtI6PBg3j | B260: Stadium Thiais | C260: played | D260: ChIJ64X9jzx05kcRsHvSfOv6UcA | E260: 48.7511024&2.3713455 | F260: 2023-11-08T21:00:00.000Z
A261: 0xyNIMd0pEjw7vnvHD2Y | B261: LE FIVE Villette | C261: played | D261: ChIJTUFnQjps5kcR0pHITLTw1PI | E261: 48.9070122&2.3861459 | F261: 2023-12-03T18:30:00.000Z
A262: 0yNsxSNdIyxtnUr5FcU8 | B262: UrbanSoccer Evry | C262: canceled | D262: ChIJW0Ut1G7e5UcRt621n2fRQ5M | E262: 48.6286849&2.4066366 | F262: 2023-12-17T17:00:00.000Z
A263: 0yV6YSjHr9xBt2lyPvGT | B263: Stadium Thiais | C263: published | D263: ChIJ64X9jzx05kcRsHvSfOv6UcA | E263: 48.7511024&2.3713455 | F263: 2023-12-25T16:30:00.000Z
A264: 0ymZE3V9JaZm8dWHrpva | B264: LE FIVE Paris 13 | C264: played | D264: ChIJ_bOSChhz5kcRZMTeq_6Gdzg | E264: 48.8181615&2.3658793 | F264: 2023-10-29T09:00:00.000Z
A265: 0yysCmsWG6Wfk86pQepa | B265: BIG5 | C265: published | D265: ChIJsb_7TJFp5kcRSPL5VqZulr4 | E265: 48.9901429&2.3617895 | F265: 2024-01-26T17:00:00.000Z
A266: 100cWiiiidozHqjzwz4E | B266: UrbanSoccer - Porte d'Aubervilliers | C266: played | D266: ChIJ0dXjDCZs5kcRvX0EpMwxsUY | E266: 48.9074912&2.3746518 | F266: 2023-11-16T19:00:00.000Z
A267: 10DCXnHRUGXhIENiIVeb | B267: Stadium Thiais | C267: published | D267: ChIJ64X9jzx05kcRsHvSfOv6UcA | E267: 48.7511024&2.3713455 | F267: 2023-12-10T16:30:00.000Z
... A288: 15GG7xf4KEPuIzVTjlHi | B288: UrbanSoccer - Asni√®res | C288: canceled | D288: ChIJi5LkLT9v5kcRSlhScqEFNWs | E288: 48.92192379999999&2.3068311 | F288: 2023-11-23T18:30:00.000Z
A289: 15KiL5TeUSm824kVDSiV | B289: LE FIVE Bezons | C289: published | D289: ChIJ71Mv0Wpk5kcRg-H9x7L-dXo | E289: 48.9190419&2.2117725
A290: 15Php1DwH89W2uXm1Tog | B290: UrbanSoccer La D√©fense | C290: canceled | D290: ChIJh4rnfVhk5kcRV2Q-ZKdm8vA | E290: 48.8996456&2.2216773 | F290: 2023-10-14T17:45:00.000Z
A291: 15gOvmMzqsel8UaqxUvA | B291: LE FIVE Villette | C291: canceled | D291: ChIJTUFnQjps5kcR0pHITLTw1PI | E291: 48.9070122&2.3861459 | F291: 2023-09-24T19:00:00.000Z
A292: 15wZCfsL7H4QfeOEYdYG | B292: We Are Sports | C292: played | D292: ChIJFZU5oBHC9EcRJTFrSkI1xxg | E292: 45.7113247&4.8761886 | F292: 2023-12-05T20:00:00.000Z
A293: 15wZFwd82IT3mq9MfM0N | B293: LE PARK Complexe Multisports | C293: played | D293: ChIJdUHbID8O5kcRV5lQhiHTvhs | E293: 48.8337843&2.5728501 | F293: 2023-09-21T19:30:00.000Z
A294: 161LUuyEezf8q5XVT4YL | B294: Play Soccer | C294: canceled | D294: ChIJQ-UxZn-5rhIRKWoQydM5T9s | E294: 43.5512023&1.4098927 | F294: 2023-09-27T18:00:00.000Z
A295: 168JXK7hr6MAEjsCHjRd | B295: Footsal | C295: canceled | D295: ChIJa7HS298pw0cRMoVDj0XqVdI | E295: 50.6397895&3.1251337 | F295: 2023-09-21T18:15:00.000Z
A296: 16LLrdnOC1ba1XgLOide | B296: Top Ten | C296: played | D296: ChIJfXprBx4b5kcRmhe-5pLZUek | E296: 48.8729106&2.6840919 | F296: 2023-12-26T21:30:00.000Z
A297: 16kO1DfQZpCcvraS8hPA | B297: Monclub Futbol | C297: played | D297: ChIJGbxxaamUyRIRgGvhHnhJStA | E297: 43.4299152&5.4001974 | F297: 2023-11-06T17:30:00.000Z
A298: 16s5D7f3zwyuuNjH7cRY | B298: Halle Georges Carpentier | C298: played | D298: ChIJnXkSwCty5kcR-nlHXNFQlg4 | E298: 48.82020139999999&2.3672361 | F298: 2024-01-25T11:00:00.000Z
A299: 16zyQgnWDnX5wXUez6Gq | B299: Complexe Sportif Marcel Cerdan | C299: played | D299: ChIJI8YbZjmJ5kcRchjITaNUFCU | E299: 48.9184115&2.0276606 | F299: 2023-09-17T07:45:00.000Z
A300: 17CrGZ7VgRU2rLGSAI8v | B300: Stadium Thiais | C300: published | D300: ChIJ64X9jzx05kcRsHvSfOv6UcA | E300: 48.7511024&2.3713455 | F300: 2023-10-24T16:30:00.000Z
A301: 17IU2u54YAerfw2orrDW | B301: UrbanSoccer - Porte d'Aubervilliers | C301: played | D301: ChIJ0dXjDCZs5kcRvX0EpMwxsUY | E301: 48.9074912&2.3746518 | F301: 2023-11-13T19:30:00.000Z
... A368: 1LsuFK2EGCZB1vYtcgeo | B368: Stadium Thiais | C368: published | D368: ChIJ64X9jzx05kcRsHvSfOv6UcA | E368: 48.7511024&2.3713455 | F368: 2024-01-13T10:30:00.000Z
A369: 1MOMw58pVZau6Sh8YhW9 | B369: Hoops Factory Paris-Villette | C369: published | D369: ChIJs1kcDDRs5kcRkbfCQVfDcyA | E369: 48.9046968&2.3794611
A370: 1McbPIopP6536wsJA08n | B370: Stadium Thiais | C370: published | D370: ChIJ64X9jzx05kcRsHvSfOv6UcA | E370: 48.7511024&2.3713455 | F370: 2024-01-20T18:00:00.000Z
A371: 1MmoCURoG7A88sRjCuFr | B371: Z5 Aix | C371: played | D371: ChIJKb-U_9KSyRIRKIFKbH5mW18 | E371: 43.4787869&5.3969048 | F371: 2023-12-03T17:00:00.000Z
A372: 1MtcFkdInUo6ZC9dcZeu | B372: Footsal | C372: played | D372: ChIJa7HS298pw0cRMoVDj0XqVdI | E372: 50.6397895&3.1251337 | F372: 2023-12-21T19:15:00.000Z
A373: 1N2lhfTAniJ1VsKWmLYM | B373: UrbanSoccer - Toulouse Sept Deniers | C373: published | D373: ChIJk5nUBdOkrhIRP-1aUJzo-lA | E373: 43.6321552&1.411696 | F373: 2023-12-13T11:30:00.000Z
A374: 1NG4X4wLQyOocBJv9EQN | B374: LE FIVE Paris 17 | C374: played | D374: ChIJ7eI8sFNv5kcR5xy52Wc57NU | E374: 48.900032&2.3213449 | F374: 2024-01-21T15:00:00.000Z
A375: 1NIs27LizAzR0PkMi56P | B375: Gymnase Dericbourg | C375: published | D375: ChIJpaQFZ6t25kcR_9A7lEqWW5w | E375: 48.77321569999999&2.3555436 | F375: 2023-09-27T18:30:00.000Z
A376: 1O53Se8webAX6zxMrwsI | B376: LE FIVE Paris 18 | C376: published | D376: ChIJpVT4_n1u5kcRzji6FdTBXXo | E376: 48.8978522&2.3700234 | F376: 2023-12-05T19:00:00.000Z
A377: 1OAeX90e0wQqKpdB2OdN | B377: LE FIVE Orl√©ans Ingr√© | C377: canceled | D377: ChIJzUFPDv_v5EcRG6gmhm_t_HA | E377: 47.9057474&1.8536754 | F377: 2023-09-19T17:00:00.000Z
A378: 1OQqoUA52sdAxdZ84eri | B378: LE FIVE Villette | C378: canceled | D378: ChIJTUFnQjps5kcR0pHITLTw1PI | E378: 48.9070122&2.3861459 | F378: 2024-01-08T19:30:00.000Z
A379: 1OWOibFCNiyYs470Xv3d | B379: LE FIVE Paris 18 | C379: canceled | D379: ChIJpVT4_n1u5kcRzji6FdTBXXo | E379: 48.8978522&2.3700234 | F379: 2023-12-12T21:00:00.000Z
...

Sheet Played+PlaceIds
A1: DOC_ID | B1: CENTRE | C1: STATUS | D1: PLACE_ID | E1: LOCATION | F1: DATE
A2: 00HTbiPPxn91ynn7qR1L | B2: UrbanSoccer - Porte d'Aubervilliers | C2: played | D2: ChIJ0dXjDCZs5kcRvX0EpMwxsUY | E2: 48.9074912&2.3746518 | F2: 2024-01-07T10:00:00.000Z
A3: 01DNdi3KlujTX6skrg3g | B3: Game 13 foot indoor | C3: played | D3: ChIJNSDvlsXryRIRUXao9hwB79I | E3: 43.41258939999999&5.366617 | F3: 2024-01-23T20:30:00.000Z
A4: 01ZbJa9fM9COMXnLynCM | B4: LE FIVE Paris 18 | C4: played | D4: ChIJpVT4_n1u5kcRzji6FdTBXXo | E4: 48.8978522&2.3700234 | F4: 2024-01-10T17:30:00.000Z
A5: 02VDY3BeIYvvYul4Tl3O | B5: UrbanSoccer - Puteaux | C5: played | D5: ChIJM_sC0-Nk5kcRhL1y_EFIje8 | E5: 48.8836397&2.2312283 | F5: 2023-11-04T12:30:00.000Z
A6: 03Alcz66wSkAUuELRV7P | B6: STADE PIERRE BOURDAN | C6: played | D6: ChIJlzXk7HLr9EcR8P0J9oTn_Pk | E6: 45.79243109999999&4.840371699999999 | F6: 2023-10-01T08:00:00.000Z
A7: 03DtLtqnJ2ZNo2pk6TTK | B7: UrbanSoccer La D√©fense | C7: played | D7: ChIJh4rnfVhk5kcRV2Q-ZKdm8vA | E7: 48.8996456&2.2216773 | F7: 2023-11-19T18:00:00.000Z
A8: 03RR9bdwDPRyQ33rcYFw | B8: UrbanSoccer - Quai d'Ivry | C8: played | D8: ChIJfXxYJ0xy5kcRw9xTkF6-FZQ | E8: 48.8199815&2.3936307 | F8: 2023-11-19T19:15:00.000Z
A9: 04gJdGYyVUukYA8MRdXI | B9: Stadium Thiais | C9: played | D9: ChIJ64X9jzx05kcRsHvSfOv6UcA | E9: 48.7511024&2.3713455 | F9: 2024-01-24T18:00:00.000Z
A10: 050PGY1dw4L8S9C2Ao3l | B10: Abd Drive | C10: played | D10: ChIJCVBWxGht5kcRclC3u2EvPKs | E10: 48.86598919999999&2.4308229 | F10: 2023-10-07T07:00:00.000Z
A11: 05RXibHd2A01CjfuXl6P | B11: Stade Makowski | C11: played | D11: ChIJvShnxJpt5kcRwdqlaq1s3E0 | E11: 48.9090365&2.436058 | F11: 2023-10-08T08:00:00.000Z
A12: 05jTyZfZ3VcOTC3urnmw | B12: LE FIVE Bezons | C12: played | D12: ChIJ71Mv0Wpk5kcRg-H9x7L-dXo | E12: 48.9190419&2.2117725 | F12: 2023-10-30T18:30:00.000Z
... A1854: Erv0PikZp7BTH3UMbITe | B1854: Stadium Thiais | C1854: played | D1854: ChIJ64X9jzx05kcRsHvSfOv6UcA | E1854: 48.7511024&2.3713455 | F1854: 2023-12-15T16:00:00.000Z
A1855: EsBcnbkRCuYGZZXMQzaT | B1855: Stade de la Tour aux Parachutes | C1855: played | D1855: ChIJbwsrhCpy5kcRca22Pnhr8MU | E1855: 48.8175176&2.3643354
A1856: EstRQJIdRgnOKXlFQc9W | B1856: LE PARK Complexe Multisports | C1856: played | D1856: ChIJdUHbID8O5kcRV5lQhiHTvhs | E1856: 48.8337843&2.5728501 | F1856: 2023-12-21T20:30:00.000Z
A1857: EvFn11KDyfTI6OUCHJac | B1857: UrbanSoccer Evry | C1857: played | D1857: ChIJW0Ut1G7e5UcRt621n2fRQ5M | E1857: 48.6286849&2.4066366 | F1857: 2023-09-29T20:15:00.000Z
A1858: EvN1UvCwgTQ0EJZoqggl | B1858: BIG5 | C1858: played | D1858: ChIJsb_7TJFp5kcRSPL5VqZulr4 | E1858: 48.9901429&2.3617895 | F1858: 2024-01-03T17:45:00.000Z
A1859: Ew6yNRPqt8OGVErtzE2C | B1859: Le 13 - Foot en salle - Marseille | C1859: played | D1859: ChIJR62kUm_ByRIRDnGQqGCeUVQ | E1859: 43.33370070000001&5.370389599999999 | F1859: 2023-12-28T19:30:00.000Z
A1860: EwToE66U3lotnxejlcDh | B1860: Evolution Football | C1860: played | D1860: ChIJX0YulIi8yRIRnGh62u3UXTQ | E1860: 43.2836074&5.52356 | F1860: 2023-11-22T18:30:00.000Z
A1861: EwaJr0iOq3zCY4C5JIJm | B1861: Gymnase Jean Blot | C1861: played | D1861: ChIJ4d5-96Nl5kcR8yiXJFyJ8Ec | E1861: 48.903562&2.253597 | F1861: 2023-10-16T18:15:00.000Z
A1862: ExJja1VIDXySto8gjuIN | B1862: Stade de l'ƒ∞le de Puteaux | C1862: played | D1862: ChIJIZUd2yJl5kcRRWoJNnmY1Ds | E1862: 48.8758697&2.2435162 | F1862: 2023-10-08T12:30:00.000Z
A1863: EyJkEKjNqfGPZg6knIUu | B1863: LE FIVE Paris 18 | C1863: played | D1863: ChIJpVT4_n1u5kcRzji6FdTBXXo | E1863: 48.8978522&2.3700234 | F1863: 2023-12-23T12:30:00.000Z
A1864: EzgmLpQWiX6ERtTVpo58 | B1864: LE FIVE Sarcelles | C1864: played | D1864: ChIJ6_q3Fxhq5kcRCpoEwnoXX1Q | E1864: 48.99782219999999&2.3902225 | F1864: 2023-12-14T19:00:00.000Z
A1865: F0cNsePOURe7LUraLmzV | B1865: OHSPORT | C1865: played | D1865: ChIJHeG9fA4X5kcRbGNzVY5Ud5I | E1865: 48.9672396&2.5670436 | F1865: 2023-10-05T19:30:00.000Z
A1866: F0kpxKyK7KawX2y4UmEv | B1866: LE FIVE Paris 18 | C1866: played | D1866: ChIJpVT4_n1u5kcRzji6FdTBXXo | E1866: 48.8978522&2.3700234 | F1866: 2023-11-10T20:00:00.000Z
A1867: F0lST0KMTuvvOVn9kzLY | B1867: Gabriel P√©ri | C1867: played | D1867: ChIJRyApR2hv5kcR1FpdLQqqHyg | E1867: 48.9162635&2.2949275 | F1867: 2023-11-12T12:10:00.000Z
... A7420: zzJEDJqFKrB6BFYNngz8 | B7420: LE FIVE Paris 18 | C7420: played | D7420: ChIJpVT4_n1u5kcRzji6FdTBXXo | E7420: 48.8978522&2.3700234 | F7420: 2023-11-19T16:30:00.000Z

Sheet Sheet2
A1: centre_name | B1: centre_place_id | C1: centre_location | D1: -
A2: Élite 5 Soccer | B2: ChIJ5-jfdlZk5kcRYIaELgvikaM | C2: =INDEX('Played+PlaceIds'!E:E,MATCH(Sheet2!B2,'Played+PlaceIds'!D:D,0)) -> 48.9009153&2.2297275 | D2: =INDEX([1]cached_centres_240126_1631!$A:$A,MATCH(B2,[1]cached_centres_240126_1631!$C:$C,0)) -> rG59DRo1lewFUT8haF7G
A3: Épidémie | B3: ChIJ01SvstEow0cREjfBiAigUhY | C3: =INDEX('Played+PlaceIds'!E:E,MATCH(Sheet2!B3,'Played+PlaceIds'!D:D,0)) -> 50.7118064&3.1661849 | D3: =INDEX([1]cached_centres_240126_1631!$A:$A,MATCH(B3,[1]cached_centres_240126_1631!$C:$C,0)) -> #N/A
A4: Abd Drive | B4: ChIJCVBWxGht5kcRclC3u2EvPKs | C4: =INDEX('Played+PlaceIds'!E:E,MATCH(Sheet2!B4,'Played+PlaceIds'!D:D,0)) -> 48.86598919999999&2.4308229 | D4: =INDEX([1]cached_centres_240126_1631!$A:$A,MATCH(B4,[1]cached_centres_240126_1631!$C:$C,0)) -> #N/A
A5: Antony | B5: ChIJf8cFRhF35kcR0D6LaMOCCwQ | C5: =INDEX('Played+PlaceIds'!E:E,MATCH(Sheet2!B5,'Played+PlaceIds'!D:D,0)) -> 48.759255&2.302553 | D5: =INDEX([1]cached_centres_240126_1631!$A:$A,MATCH(B5,[1]cached_centres_240126_1631!$C:$C,0)) -> #N/A
A6: Arena Club | B6: ChIJeWJWRjYvw0cRbnJR4ZXAKMA | C6: =INDEX('Played+PlaceIds'!E:E,MATCH(Sheet2!B6,'Played+PlaceIds'!D:D,0)) -> 50.7696017&3.1236104 | D6: =INDEX([1]cached_centres_240126_1631!$A:$A,MATCH(B6,[1]cached_centres_240126_1631!$C:$C,0)) -> #N/A
A7: B14 - Sports et Loisirs Indoor | B7: ChIJaeLKMYXe5UcRHyWJ8X8FaPA | C7: =INDEX('Played+PlaceIds'!E:E,MATCH(Sheet2!B7,'Played+PlaceIds'!D:D,0)) -> 48.62229&2.3800445 | D7: =INDEX([1]cached_centres_240126_1631!$A:$A,MATCH(B7,[1]cached_centres_240126_1631!$C:$C,0)) -> #N/A
A8: BIG5 | B8: ChIJsb_7TJFp5kcRSPL5VqZulr4 | C8: =INDEX('Played+PlaceIds'!E:E,MATCH(Sheet2!B8,'Played+PlaceIds'!D:D,0)) -> 48.9901429&2.3617895 | D8: =INDEX([1]cached_centres_240126_1631!$A:$A,MATCH(B8,[1]cached_centres_240126_1631!$C:$C,0)) -> #N/A
A9: Cap Loisirs | B9: ChIJ6xl7EP2irhIRG2TbDQazLzE | C9: =INDEX('Played+PlaceIds'!E:E,MATCH(Sheet2!B9,'Played+PlaceIds'!D:D,0)) -> 43.64393279999999&1.4791113 | D9: =INDEX([1]cached_centres_240126_1631!$A:$A,MATCH(B9,[1]cached_centres_240126_1631!$C:$C,0)) -> #N/A
A10: Classico Foot | B10: ChIJFV442oCxrhIRgsZy5aIbkNs | C10: =INDEX('Played+PlaceIds'!E:E,MATCH(Sheet2!B10,'Played+PlaceIds'!D:D,0)) -> 43.5945434&1.2911399 | D10: =INDEX([1]cached_centres_240126_1631!$A:$A,MATCH(B10,[1]cached_centres_240126_1631!$C:$C,0)) -> #N/A
A11: Events Five | B11: ChIJf8cSCJG5rhIRoQadPH-wW1U | C11: =INDEX('Played+PlaceIds'!E:E,MATCH(Sheet2!B11,'Played+PlaceIds'!D:D,0)) -> 43.5399703&1.3922897 | D11: =INDEX([1]cached_centres_240126_1631!$A:$A,MATCH(B11,[1]cached_centres_240126_1631!$C:$C,0)) -> #N/A
A12: Evolution Football | B12: ChIJX0YulIi8yRIRnGh62u3UXTQ | C12: =INDEX('Played+PlaceIds'!E:E,MATCH(Sheet2!B12,'Played+PlaceIds'!D:D,0)) -> 43.2836074&5.52356 | D12: =INDEX([1]cached_centres_240126_1631!$A:$A,MATCH(B12,[1]cached_centres_240126_1631!$C:$C,0)) -> #N/A
A13: F5 Foot Five | B13: ChIJjUbM5G7A9EcRW3mlkrhyXxY | C13: =INDEX('Played+PlaceIds'!E:E,MATCH(Sheet2!B13,'Played+PlaceIds'!D:D,0)) -> 45.7857911&4.905926399999999 | D13: =INDEX([1]cached_centres_240126_1631!$A:$A,MATCH(B13,[1]cached_centres_240126_1631!$C:$C,0)) -> #N/A
... A100: Z5 Aix | B100: ChIJKb-U_9KSyRIRKIFKbH5mW18 | C100: =INDEX('Played+PlaceIds'!E:E,MATCH(Sheet2!B100,'Played+PlaceIds'!D:D,0)) -> 43.4787869&5.3969048 | D100: =INDEX([1]cached_centres_240126_1631!$A:$A,MATCH(B100,[1]cached_centres_240126_1631!$C:$C,0)) -> #N/A
